sentinel/__init__.py
sentinel/errors.py
sentinel/handlers/__init__.py
sentinel/handlers/slash.py
sentinel/rest/__init__.py
sentinel/rest/http.py
sentinel/rest/ws.py
sentinel/struct/__init__.py
sentinel/struct/client.py
sentinel/struct/types/__init__.py
sentinel/struct/types/activity.py
sentinel/struct/types/context.py
sentinel/struct/types/embed.py
sentinel/struct/types/status.py
sentinel/struct/types/user.py
sentinel/utils/__init__.py
sentinel/utils/constants.py
sentinel/utils/payloads.py
sentinel/utils/utils.py
sentinel_python-0.0.2.dist-info/LICENSE
sentinel_python-0.0.2.dist-info/METADATA
sentinel_python-0.0.2.dist-info/WHEEL
sentinel_python-0.0.2.dist-info/top_level.txt
sentinel_python-0.0.2.dist-info/RECORD
