Metadata-Version: 2.1
Name: sentinel-python
Version: 0.0.2
Summary: Package for using Discord slash commands
Home-page: UNKNOWN
Author: xezzz
Author-email: ezzz.btw@gmail.com
License: UNKNOWN
Platform: UNKNOWN
Classifier: Development Status :: 1 - Planning
Classifier: Intended Audience :: Developers
Classifier: Programming Language :: Python :: 3
Classifier: Operating System :: OS Independent
Requires-Dist: websocket-client
Requires-Dist: aiohttp
